pycascor/__init__.py
pycascor/activation_functions.py
pycascor/learning_algorithms.py
pycascor/network.py
pycascor/nodes.py
pycascor/trainer.py
pycascor-0.1.2.dist-info/LICENSE.txt
pycascor-0.1.2.dist-info/METADATA
pycascor-0.1.2.dist-info/WHEEL
pycascor-0.1.2.dist-info/top_level.txt
pycascor-0.1.2.dist-info/RECORD
