Metadata-Version: 2.1
Name: pycascor
Version: 0.1.2
Summary: Cascade Correlation Network Simulator
Author-email: Caroline Simpson <pycascor@hoojiboo.com>
Maintainer-email: Caroline Simpson <pycascor@hoojiboo.com>
License: MIT License
Project-URL: Repository, https://gitlab.com/cpsimpson/cascade-correlation-network-simulator
Project-URL: Bug Tracker, https://gitlab.com/cpsimpson/cascade-correlation-network-simulator/-/issues
Keywords: Cascade Correlation,neural network,cascor
Classifier: License :: OSI Approved :: MIT License
Classifier: Programming Language :: Python
Classifier: Programming Language :: Python :: 3
Requires-Python: >=3.8
License-File: LICENSE.txt
Requires-Dist: numpy >=1.8
Requires-Dist: matplotlib >=3.0
